[
  { "country": "Afghanistan", "capital": "Kabul", "languages": ["Dari", "Pashto"], "continent": "Asia" },
  { "country": "Albania", "capital": "Tirana", "languages": ["Albanian"], "continent": "Europe" },
  { "country": "Algeria", "capital": "Algiers", "languages": ["Arabic", "Berber"], "continent": "Africa" },
  { "country": "Andorra", "capital": "Andorra la Vella", "languages": ["Catalan"], "continent": "Europe" },
  { "country": "Angola", "capital": "Luanda", "languages": ["Portuguese"], "continent": "Africa" },
  { "country": "Antigua and Barbuda", "capital": "Saint John's", "languages": ["English"], "continent": "North America" },
  { "country": "Argentina", "capital": "Buenos Aires", "languages": ["Spanish"], "continent": "South America" },
  { "country": "Armenia", "capital": "Yerevan", "languages": ["Armenian"], "continent": "Asia" },
  { "country": "Australia", "capital": "Canberra", "languages": ["English"], "continent": "Oceania" },
  { "country": "Austria", "capital": "Vienna", "languages": ["German"], "continent": "Europe" },
  { "country": "Azerbaijan", "capital": "Baku", "languages": ["Azerbaijani"], "continent": "Asia" },
  { "country": "Bahamas", "capital": "Nassau", "languages": ["English"], "continent": "North America" },
  { "country": "Bahrain", "capital": "Manama", "languages": ["Arabic"], "continent": "Asia" },
  { "country": "Bangladesh", "capital": "Dhaka", "languages": ["Bengali"], "continent": "Asia" },
  { "country": "Barbados", "capital": "Bridgetown", "languages": ["English"], "continent": "North America" },
  { "country": "Belarus", "capital": "Minsk", "languages": ["Belarusian", "Russian"], "continent": "Europe" },
  { "country": "Belgium", "capital": "Brussels", "languages": ["Dutch", "French", "German"], "continent": "Europe" },
  { "country": "Belize", "capital": "Belmopan", "languages": ["English"], "continent": "North America" },
  { "country": "Benin", "capital": "Porto-Novo", "languages": ["French"], "continent": "Africa" },
  { "country": "Bhutan", "capital": "Thimphu", "languages": ["Dzongkha"], "continent": "Asia" },
  { "country": "Bolivia", "capital": "Sucre (constitutional), La Paz (seat of government)", "languages": ["Spanish", "Quechua", "Aymara"], "continent": "South America" },
  { "country": "Bosnia and Herzegovina", "capital": "Sarajevo", "languages": ["Bosnian", "Croatian", "Serbian"], "continent": "Europe" },
  { "country": "Botswana", "capital": "Gaborone", "languages": ["English", "Tswana"], "continent": "Africa" },
  { "country": "Brazil", "capital": "Brasília", "languages": ["Portuguese"], "continent": "South America" },
  { "country": "Brunei", "capital": "Bandar Seri Begawan", "languages": ["Malay"], "continent": "Asia" },
  { "country": "Bulgaria", "capital": "Sofia", "languages": ["Bulgarian"], "continent": "Europe" },
  { "country": "Burkina Faso", "capital": "Ouagadougou", "languages": ["French"], "continent": "Africa" },
  { "country": "Burundi", "capital": "Bujumbura", "languages": ["Kirundi", "French", "English"], "continent": "Africa" },
  { "country": "Cabo Verde", "capital": "Praia", "languages": ["Portuguese"], "continent": "Africa" },
  { "country": "Cambodia", "capital": "Phnom Penh", "languages": ["Khmer"], "continent": "Asia" },
  { "country": "Cameroon", "capital": "Yaoundé", "languages": ["English", "French"], "continent": "Africa" },
  { "country": "Canada", "capital": "Ottawa", "languages": ["English", "French"], "continent": "North America" },
  { "country": "Central African Republic", "capital": "Bangui", "languages": ["French", "Sango"], "continent": "Africa" },
  { "country": "Chad", "capital": "N'Djamena", "languages": ["French", "Arabic"], "continent": "Africa" },
  { "country": "Chile", "capital": "Santiago", "languages": ["Spanish"], "continent": "South America" },
  { "country": "China", "capital": "Beijing", "languages": ["Chinese"], "continent": "Asia" },
  { "country": "Colombia", "capital": "Bogotá", "languages": ["Spanish"], "continent": "South America" },
  { "country": "Comoros", "capital": "Moroni", "languages": ["Comorian", "Arabic", "French"], "continent": "Africa" },
  { "country": "Congo (Republic of the)", "capital": "Brazzaville", "languages": ["French"], "continent": "Africa" },
  { "country": "Congo (Democratic Republic of the)", "capital": "Kinshasa", "languages": ["French"], "continent": "Africa" },
  { "country": "Costa Rica", "capital": "San José", "languages": ["Spanish"], "continent": "North America" },
  { "country": "Croatia", "capital": "Zagreb", "languages": ["Croatian"], "continent": "Europe" },
  { "country": "Cuba", "capital": "Havana", "languages": ["Spanish"], "continent": "North America" },
  { "country": "Cyprus", "capital": "Nicosia", "languages": ["Greek", "Turkish"], "continent": "Asia" },
  { "country": "Czech Republic", "capital": "Prague", "languages": ["Czech"], "continent": "Europe" },
  { "country": "Denmark", "capital": "Copenhagen", "languages": ["Danish"], "continent": "Europe" },
  { "country": "Djibouti", "capital": "Djibouti City", "languages": ["Arabic", "French"], "continent": "Africa" },
  { "country": "Dominica", "capital": "Roseau", "languages": ["English"], "continent": "North America" },
  { "country": "Dominican Republic", "capital": "Santo Domingo", "languages": ["Spanish"], "continent": "North America" },
  { "country": "Ecuador", "capital": "Quito", "languages": ["Spanish"], "continent": "South America" },
  { "country": "Egypt", "capital": "Cairo", "languages": ["Arabic"], "continent": "Africa" },
  { "country": "El Salvador", "capital": "San Salvador", "languages": ["Spanish"], "continent": "North America" },
  { "country": "Equatorial Guinea", "capital": "Malabo", "languages": ["Spanish", "French", "Portuguese"], "continent": "Africa" },
  { "country": "Eritrea", "capital": "Asmara", "languages": ["Tigrinya", "Arabic", "English"], "continent": "Africa" },
  { "country": "Estonia", "capital": "Tallinn", "languages": ["Estonian"], "continent": "Europe" },
  { "country": "Eswatini", "capital": "Mbabane (administrative), Lobamba (royal and legislative)", "languages": ["Swazi", "English"], "continent": "Africa" },
  { "country": "Ethiopia", "capital": "Addis Ababa", "languages": ["Amharic"], "continent": "Africa" },
  { "country": "Fiji", "capital": "Suva", "languages": ["English", "Fijian", "Hindustani"], "continent": "Oceania" },
  { "country": "Finland", "capital": "Helsinki", "languages": ["Finnish", "Swedish"], "continent": "Europe" },
  { "country": "France", "capital": "Paris", "languages": ["French"], "continent": "Europe" },
  { "country": "Gabon", "capital": "Libreville", "languages": ["French"], "continent": "Africa" },
  { "country": "Gambia", "capital": "Banjul", "languages": ["English"], "continent": "Africa" },
  { "country": "Georgia", "capital": "Tbilisi", "languages": ["Georgian"], "continent": "Asia" },
  { "country": "Germany", "capital": "Berlin", "languages": ["German"], "continent": "Europe" },
  { "country": "Ghana", "capital": "Accra", "languages": ["English"], "continent": "Africa" },
  { "country": "Greece", "capital": "Athens", "languages": ["Greek"], "continent": "Europe" },
  { "country": "Grenada", "capital": "St. George's", "languages": ["English"], "continent": "North America" },
  { "country": "Guatemala", "capital": "Guatemala City", "languages": ["Spanish"], "continent": "North America" },
  { "country": "Guinea", "capital": "Conakry", "languages": ["French"], "continent": "Africa" },
  { "country": "Guinea-Bissau", "capital": "Bissau", "languages": ["Portuguese"], "continent": "Africa" },
  { "country": "Guyana", "capital": "Georgetown", "languages": ["English"], "continent": "South America" },
  { "country": "Haiti", "capital": "Port-au-Prince", "languages": ["Haitian Creole", "French"], "continent": "North America" },
  { "country": "Honduras", "capital": "Tegucigalpa", "languages": ["Spanish"], "continent": "North America" },
  { "country": "Hungary", "capital": "Budapest", "languages": ["Hungarian"], "continent": "Europe" }
]
